rawabs2rel.py
rawabs2rel-1.1.0.dist-info/METADATA
rawabs2rel-1.1.0.dist-info/WHEEL
rawabs2rel-1.1.0.dist-info/RECORD
